cronio/__init__.py
cronio/utils.py
cronio/sender/__init__.py
cronio/worker/__init__.py
cronio/worker/models.py
cronio-1.2.0.dist-info/METADATA
cronio-1.2.0.dist-info/RECORD
cronio-1.2.0.dist-info/WHEEL
cronio-1.2.0.dist-info/top_level.txt
tests/__init__.py
tests/context.py
tests/test_basic.py
