Metadata-Version: 2.1
Name: cronio
Version: 1.2.0
Summary: This project has a sender and a receiver, the sender sends commands through RabbitMQ on the queue of a worker (receiver), the receiver executes them either with OS or Python2.7
Home-page: https://github.com/nvalerkos/cronio
Author: Nikolas Valerkos
Author-email: n.valerkos@gmail.com
License: UNKNOWN
Platform: UNKNOWN
Classifier: Programming Language :: Python :: 2
Classifier: License :: OSI Approved :: MIT License
Classifier: Operating System :: OS Independent
Requires-Dist: stomp-py
Requires-Dist: sqlalchemy
